CONTRIBUTORS.txt
LICENSE.txt
MANIFEST.in
README.md
setup.cfg
setup.py
Flask_KQMaps.egg-info/PKG-INFO
Flask_KQMaps.egg-info/SOURCES.txt
Flask_KQMaps.egg-info/dependency_links.txt
Flask_KQMaps.egg-info/requires.txt
Flask_KQMaps.egg-info/top_level.txt
flask_kqmaps/__init__.py
flask_kqmaps/static/kqwebclient/leaflet/include-leaflet.js
flask_kqmaps/static/kqwebclient/leaflet/kq-es5.js
flask_kqmaps/static/kqwebclient/leaflet/kq-release.js
flask_kqmaps/static/kqwebclient/leaflet/3rd_libs/readme.txt
flask_kqmaps/static/kqwebclient/leaflet/3rd_libs/Leaflet-Coordinates-Control/Control.Coordinates.css
flask_kqmaps/static/kqwebclient/leaflet/3rd_libs/Leaflet-Coordinates-Control/Control.Coordinates.js
flask_kqmaps/static/kqwebclient/leaflet/3rd_libs/Leaflet-Coordinates-Control/LICENSE.md
flask_kqmaps/static/kqwebclient/leaflet/3rd_libs/Leaflet-Coordinates-Control/README.md
flask_kqmaps/static/kqwebclient/leaflet/3rd_libs/Leaflet-arrowheads/index.js
flask_kqmaps/static/kqwebclient/leaflet/3rd_libs/Leaflet-arrowheads/leaflet-arrowheads.js
flask_kqmaps/static/kqwebclient/leaflet/3rd_libs/Leaflet-arrowheads/leaflet-geometryutil.js
flask_kqmaps/static/kqwebclient/leaflet/3rd_libs/Leaflet-semicircle/Semicircle.js
flask_kqmaps/static/kqwebclient/leaflet/3rd_libs/Leaflet.AntPath/leaflet-ant-path.es6.js
flask_kqmaps/static/kqwebclient/leaflet/3rd_libs/Leaflet.AntPath/leaflet-ant-path.es6.js.map
flask_kqmaps/static/kqwebclient/leaflet/3rd_libs/Leaflet.AntPath/leaflet-ant-path.js
flask_kqmaps/static/kqwebclient/leaflet/3rd_libs/Leaflet.AntPath/leaflet-ant-path.js.map
flask_kqmaps/static/kqwebclient/leaflet/3rd_libs/Leaflet.Canvas-Flowmap-Layer/CanvasFlowmapLayer.js
flask_kqmaps/static/kqwebclient/leaflet/3rd_libs/Leaflet.Canvas-Markers/leaflet.canvas-markers.js
flask_kqmaps/static/kqwebclient/leaflet/3rd_libs/Leaflet.Control.Custom/Leaflet.Control.Custom.js
flask_kqmaps/static/kqwebclient/leaflet/3rd_libs/Leaflet.CustomLayer/Leaflet.CustomLayer.esm.js
flask_kqmaps/static/kqwebclient/leaflet/3rd_libs/Leaflet.CustomLayer/Leaflet.CustomLayer.esm.js.map
flask_kqmaps/static/kqwebclient/leaflet/3rd_libs/Leaflet.CustomLayer/Leaflet.CustomLayer.js
